yaow/VERSION
yaow/__init__.py
yaow/arguments.yaml
yaow/cli.py
yaow-0.0.1.dist-info/LICENSE
yaow-0.0.1.dist-info/METADATA
yaow-0.0.1.dist-info/WHEEL
yaow-0.0.1.dist-info/entry_points.txt
yaow-0.0.1.dist-info/top_level.txt
yaow-0.0.1.dist-info/RECORD
