Metadata-Version: 2.1
Name: yaow
Version: 0.0.1
Summary: Yet another openconnect wrapper.
Home-page: https://github.com/alphabet5/yaow
Author: alphabet5
Classifier: Programming Language :: Python :: 3
Classifier: License :: OSI Approved :: MIT License
Classifier: Operating System :: OS Independent
Requires-Python: >=3.9
License-File: LICENSE
Requires-Dist: validators
Requires-Dist: yamlarg
Requires-Dist: keyring
Requires-Dist: pyotp
Requires-Dist: O365
Requires-Dist: rich
